botasaurus/__init__.py
botasaurus/_id.py
botasaurus/accept_google_cookies.py
botasaurus/anti_detect_driver.py
botasaurus/anti_detect_requests.py
botasaurus/base_data.py
botasaurus/beep_utils.py
botasaurus/botasaurus_storage.py
botasaurus/bt.py
botasaurus/cache.py
botasaurus/calc_max_parallel_browsers.py
botasaurus/captcha.py
botasaurus/check_and_download_driver.py
botasaurus/chrome_launcher_adapter.py
botasaurus/cl.py
botasaurus/close.py
botasaurus/constants.py
botasaurus/create_driver_utils.py
botasaurus/create_stealth_driver.py
botasaurus/creators.py
botasaurus/decorator_helpers.py
botasaurus/decorators.py
botasaurus/decorators_utils.py
botasaurus/download_driver.py
botasaurus/driver_about.py
botasaurus/exceptions.py
botasaurus/formats.py
botasaurus/get_chrome_version.py
botasaurus/got_adapter.py
botasaurus/ip_utils.py
botasaurus/list_utils.py
botasaurus/local_storage.py
botasaurus/local_storage_driver.py
botasaurus/opponent.py
botasaurus/output.py
botasaurus/profile.py
botasaurus/shortcuts.py
botasaurus/sitemap.py
botasaurus/str_utils.py
botasaurus/temp_mail.py
botasaurus/usage.py
botasaurus/user_agent.py
botasaurus/user_generator.py
botasaurus/utils.py
botasaurus/wait.py
botasaurus/window_size.py
botasaurus2-1.4.13.dist-info/AUTHORS
botasaurus2-1.4.13.dist-info/LICENSE
botasaurus2-1.4.13.dist-info/METADATA
botasaurus2-1.4.13.dist-info/WHEEL
botasaurus2-1.4.13.dist-info/RECORD
