Metadata-Version: 2.1
Name: botasaurus2
Version: 1.4.13
Summary: Patching fork of botasaurus, The All in One Framework to build Awesome Scrapers.
License: MIT
Author: Chetan Jain
Author-email: chetan@omkar.cloud
Requires-Python: >=3.10,<4.0
Classifier: License :: OSI Approved :: MIT License
Classifier: Programming Language :: Python :: 3
Classifier: Programming Language :: Python :: 3.10
Classifier: Programming Language :: Python :: 3.11
Classifier: Programming Language :: Python :: 3.12
Requires-Dist: aigents (>=0.7.2)
Requires-Dist: beautifulsoup4 (>=4.11.2,<5.0.0)
Requires-Dist: botasaurus-proxy-authentication (>=1.0.12,<2.0.0)
Requires-Dist: capsolver-extension-python (>=1.0.1,<2.0.0)
Requires-Dist: chromedriver-autoinstaller-fix (>=1.0.6,<2.0.0)
Requires-Dist: cloudscraper (>=1.2.71,<2.0.0)
Requires-Dist: javascript-fixes (>=1.1.21,<2.0.0)
Requires-Dist: joblib (>=1.3.2,<2.0.0)
Requires-Dist: lxml (>=5.1.0,<6.0.0)
Requires-Dist: packaging (>=24.0,<25.0)
Requires-Dist: psutil (>=5.9.8,<6.0.0)
Requires-Dist: requests (>=2.31.0,<3.0.0)
Requires-Dist: selenium (>=4.9.0,<5.0.0)
